ib_fundamental/__init__.py
ib_fundamental/fundamental.py
ib_fundamental/ib_client.py
ib_fundamental/objects.py
ib_fundamental/utils.py
ib_fundamental/xml_parser.py
ib_fundamental/xml_report.py
ib_fundamental-0.0.5.dist-info/LICENSE.txt
ib_fundamental-0.0.5.dist-info/METADATA
ib_fundamental-0.0.5.dist-info/WHEEL
ib_fundamental-0.0.5.dist-info/top_level.txt
ib_fundamental-0.0.5.dist-info/RECORD
