Metadata-Version: 2.1
Name: ib_fundamental
Version: 0.0.5
Summary: Interactive Brokers Fundamental data for humans
Author: gnzsnz
License: Apache License
Project-URL: Homepage, https://github.com/quantbelt/ib_fundamental
Project-URL: Bug Tracker, https://github.com/quantbelt/ib_fundamental/issues
Classifier: Programming Language :: Python :: 3
Classifier: License :: OSI Approved :: Apache Software License
Classifier: Operating System :: OS Independent
Classifier: Development Status :: 3 - Alpha
Requires-Python: >=3.10
License-File: LICENSE.txt
Requires-Dist: ib-async >=1.0.1
Requires-Dist: pandas >=2.2.2
Requires-Dist: defusedxml >=0.7.1
Provides-Extra: dev
Requires-Dist: black >=24.4.2 ; extra == 'dev'
Requires-Dist: pylint >=3.1.1 ; extra == 'dev'
Requires-Dist: isort >=5.13.2 ; extra == 'dev'
Requires-Dist: mypy >=1.10.0 ; extra == 'dev'
Requires-Dist: pre-commit >=3.7.1 ; extra == 'dev'
Requires-Dist: pandas-stubs >=2.2.1.240316 ; extra == 'dev'
Requires-Dist: bandit[toml] >=1.7.8 ; extra == 'dev'
Requires-Dist: flake8 >=7.0.0 ; extra == 'dev'
Requires-Dist: flake8-pytest-style >=2.0.0 ; extra == 'dev'
Requires-Dist: pytest >=8.2.1 ; extra == 'dev'
Requires-Dist: pytest-env >=1.1.3 ; extra == 'dev'
Requires-Dist: pytest-cov >=4.1.0 ; extra == 'dev'
Requires-Dist: pylint-pytest >=1.1.7 ; extra == 'dev'
Requires-Dist: tox >=4.0.0 ; extra == 'dev'
